{"input_text": "King, Richards and Roy\n\nEmail:smithjettrey@example.net\nBill to:Nicole Bradshaw\n\n618 Jerome Port Apt. 979\n\nEast Gabriel, NV 21298 US\nTel:(254)037-6889\nEmail:hyoder@example.com\nSite:https:/iwww.schaefer.com/\n\nItem\n\n‘Computer.\n\nLast\n\nThemselves kind order mouth.\nSign approach.\n\nCOMMERCIAL INVOICE\nINVOICE # 5741-318\n\nNote:\nThis order is shipped through blue dart courier\n\nInvoice Date: 25-Feb-2004\n\nPrice Quantity Amount\n82.53 1.00 82.53\n91.08 5.00 455.40\n64.49 6.00 386.94\n62.30 5.00 311.50\n\nTOTAL : 1288.52 EUR\n\nTotal in words: one thousand, two hundred an-\n\ndeighty-eight point five two", "target_text": "{\"seller\": {\"name\": \"King, Richards and Roy\", \"email\": \"smithjettrey@example.net\"}, \"buyer\": {\"name\": \"618 Jerome Port Apt. 979\"}, \"invoice\": {\"number\": \"5741-318\", \"date\": \"25-Feb-2004\"}, \"items\": [{\"price\": \"82.53\", \"quantity\": \"1.00\", \"amount\": \"82.53\"}, {\"price\": \"91.08\", \"quantity\": \"5.00\", \"amount\": \"455.40\"}, {\"price\": \"64.49\", \"quantity\": \"6.00\", \"amount\": \"386.94\"}, {\"price\": \"62.30\", \"quantity\": \"5.00\", \"amount\": \"311.50\"}], \"sub_total\": null, \"due_amount\": \"1288.52\", \"currency\": \"EUR\", \"amount_in_words\": \"one thousand, two hundred an-\", \"notes\": \"This order is shipped through blue dart courier\"}"}
{"input_text": "Address:16424 Timothy Mission\nMarkville, AK 58294 US.\n\nEmail:melvindo@example.net\n‘www.ThompsonandSons.org\n(GSTIN: 12345670 00070007\n\nCOMMERCIAL INVOICE\n\nInvoice Date: 12-Mar-2009\nDue Date : 20-Jun-1995\nPO Number :46\n\nBill to:Angel Bailey\n\n265 Ochoa Manors Apt. 518\nNorth John, MD 41885 US\nTol:+(675)553-3428,\nEmail:baileygary@example.net\nSite:https://www.mecormick.com/\n\nGSTIN: OG@AAMFCO376K124\n\nTEMS QUANTITY, PRICE\nHert why compare 1.00 $55.98\nGeneration task 500 $22.16\nMost indeed. 6.00 $0476\n\nTotal in words: seven hundred and forty-\n\n-four point three eight\n\nBankName Central Bank of Europe\n\nBranch Name Raf CAMP.\nBank Account Number 10180775\nBank Swift Code SBININBB250\n\n‘Thank you for choosing us!\n\n‘SUB_TOTAL : 735.29 EUR\nDISCOUNT(3.67%): (.) 26.99.\nTAX:VAT (3.10%): 22.77 EUR\n\nTOTAL : 744.38 EUR", "target_text": "{\"seller\": {\"name\": \"Markville, AK 58294 US.\", \"email\": \"melvindo@example.net\"}, \"buyer\": {\"name\": \"265 Ochoa Manors Apt. 518\"}, \"invoice\": {\"date\": \"12-Mar-2009\", \"due_date\": \"20-Jun-1995\"}, \"items\": [], \"sub_total\": \"735.29\", \"due_amount\": \"744.38\", \"currency\": \"EUR\", \"amount_in_words\": \"seven hundred and forty-\", \"notes\": \"\"}"}
{"input_text": "Address:16424 Timothy Mission\nMarkville, AK 58294 US.\n\nEmail:melvindo@example.net\n‘www.ThompsonandSons.org\n(GSTIN: 12345670 00070007\n\nINVOICE\n\nInvoice Date: 11-Aug-2017\nDue Date : 23-May-2000\nPO Number :99\n\n193 Troy Radial\nCrossborough, NV 81506 US.\nTol:+(908)834-1601\nEmail:johnsonkarina@example.org\nSite:http:/livingston.com/\n\nGSTIN: OG@AAMFCO376K124\n\nTEMS QUANTITY, PRICE\nGas. 1.00 $65.28\n\nCouple wide election. 2.00 $2539\nRight school step. 2.00 $86.37\n\nTotal in words: two hundred and nin«\n\nty-one point six nine\nBank Name\n\nBranch Name Raf CAMP.\nBank Account Number 18865073\nBank Swift Code SBININBB250\n\n‘Thank you for choosing us!\n\n‘State Bank of Texas\n\n‘SUB_TOTAL : 286.76 $\nDISCOUNT(4.43%): (-) 12.7\nTAX:VAT (5.35%): 15.34 §\n\nTOTAL : 291.69§", "target_text": "{\"seller\": {\"name\": \"Markville, AK 58294 US.\", \"email\": \"melvindo@example.net\"}, \"buyer\": {}, \"invoice\": {\"date\": \"11-Aug-2017\", \"due_date\": \"23-May-2000\"}, \"items\": [], \"sub_total\": \"286.76\", \"due_amount\": \"291.69\", \"currency\": \"\", \"amount_in_words\": \"two hundred and nin\", \"notes\": \"\"}"}
{"input_text": "TAX INVOICE\n\nInvoice Date: 18-Mar-2001\nDue Date : 09-Sep-2010\n\nPO Number :49\nAddress:16424 Timothy Mission Buyer :David Aguirre\nMarkville, AK 58294 US. 917 Mcclain Streets Apt. 454\nMoralesburgh, FM 84325 US\nEmail:melvin40@example.net Tel:+(221)488-0938\n‘www.ThompsonandSons.org Email:rsmith@example.net\n(GSTIN: 12345670 00070007 Site:http://www.morton.com/\n\nGSTIN: OG@AAMFCO376K124\n\nTEMS QUANTITY, PRICE\n‘Artve situation paper Bil 1.00 $4301\n‘Change what 4.00 $46.18\n\nTotal in words: two hundred and thirt-\ny-four point eight two\n\nBank Name Central Bank of Europe\nBranch Name Raf CAMP.\n\nBank Account Number 13551954\n\nBank Swift Code SBININBB250\n\nNote:\nThis order is shipped through blue dart couri\n\n‘SUB_TOTAL : 227.73 EUR\nDISCOUNT(2.82%): (-) 6.42\nTAX:VAT (4.34%): 9.89 EUR\n\nTOTAL : 234.82 EUR", "target_text": "{\"seller\": {\"name\": \"Due Date : 09-Sep-2010\", \"email\": \"melvin40@example.net\"}, \"buyer\": {}, \"invoice\": {\"date\": \"18-Mar-2001\", \"due_date\": \"09-Sep-2010\"}, \"items\": [], \"sub_total\": \"227.73\", \"due_amount\": \"234.82\", \"currency\": \"EUR\", \"amount_in_words\": \"two hundred and thirt-\", \"notes\": \"This order is shipped through blue dart couri\"}"}
{"input_text": "Address:16424 Timothy Mission\nMarkville, AK 58294 US.\n\nEmail:melvindo@example.net\n‘www.ThompsonandSons.org\n(GSTIN: 12345670 00070007\n\nTEMS\n\nTAX INVOICE\n\nInvoice Date: 19-Feb-1993\nDue Date : 28-Dec-1994\nPO Number :09\n\nBuyer :Adam Coleman\n\n807 Michael Rue Suite 693\n\nNorth Christopherborough, VI 18338 US\nTol:+(469)618-2664\nEmail:thomasgregg@example.net\nSite:https://www.allen-kaufman.org/\n\nGSTIN: OG@AAMFCO376K124\n\nQUANTITY, PRICE\n\nSpace of. 4.00 $001\nBoth argue wall 3.00 $226\n‘Across other 6.00 $45.73\n\nTotal in words: two hundred and eig-\n\nhty-four point five\nBank Name\nBranch Name Raf CAMP.\nBank Account Number 13380562\nBank Swift Code SBININBB250\n\nNote: All payments to be made in cash.\n\n‘State Bank of England\n\n‘SUB_TOTAL : 281.20 EUR\nDISCOUNT(3.99%): (-) 11.22\nTAX:VAT (5.84%): 16.43 EUR\n\nTOTAL : 284.50 EUR\n\nContact us for queries on these quotations.", "target_text": "{\"seller\": {\"name\": \"Markville, AK 58294 US.\", \"email\": \"melvindo@example.net\"}, \"buyer\": {\"name\": \"807 Michael Rue Suite 693\"}, \"invoice\": {\"date\": \"19-Feb-1993\", \"due_date\": \"28-Dec-1994\"}, \"items\": [], \"sub_total\": \"281.20\", \"due_amount\": \"284.50\", \"currency\": \"EUR\", \"amount_in_words\": \"two hundred and eig-\", \"notes\": \"All payments to be made in cash.\"}"}
{"input_text": "Address:16424 Timothy Mission\nMarkville, AK 58294 US.\n\nEmail:melvindo@example.net\n‘www.ThompsonandSons.org\n(GSTIN: 12345670 00070007\n\nTAX INVOICE\n\nInvoice Date: 19-Feb-2011\nDue Date : 10-Dec-2013,\n\nBill o:Timothy Oliver\n8822 Rodney Lakes Suite 027\nChristopherport, PR 92451 US\nTol:+(726)392-3224\nEmail:tramirez@example.net\nSite:http://fleming.com/\n\nGSTIN: OG@AAMFCO376K124\n\nEMS QUANTITY, PRICE\n‘Your station particular 6.00 $53.80\nWhether. 2.00 $316\nEducation message 6.00 $2931\nFive account few. 3.00 $54.66\n\nTotal in words: six hundred and ni\ny-one point three two\n\nBankName State Bank of Europe\nBranch Name Raf CAMP.\n\nBank Account Number 14081977\n\nBank Swift Code SBININBB250\n\nNote: All payments to be made in cash.\nContact us for queries on these quotations.\n\n‘SUB_TOTAL : 668.96 $\nDISCOUNT(3.28%): (-) 21.94\nTAX:VAT (6.65%): 44.50 $\n\nTOTAL : 691.325", "target_text": "{\"seller\": {\"name\": \"Markville, AK 58294 US.\", \"email\": \"melvindo@example.net\"}, \"buyer\": {}, \"invoice\": {\"date\": \"19-Feb-2011\", \"due_date\": \"10-Dec-2013\"}, \"items\": [], \"sub_total\": \"668.96\", \"due_amount\": \"691.325\", \"currency\": \"\", \"amount_in_words\": \"six hundred and ni\", \"notes\": \"All payments to be made in cash.\\nContact us for queries on these quotations.\"}"}
{"input_text": "Address:16424 Timothy Mission\nMarkville, AK 58294 US.\n\nEmail:melvindo@example.net\n‘www.ThompsonandSons.org\n(GSTIN: 12345670 00070007\n\nTAX INVOICE\n\nInvoice Date: 21-Jul-1995\nDue Date : 07-May-1998\nPO Number 64\n\nBill o:April Johnson\n979 Nixon Loop Apt. 299\n\nClementstown, Vi 98807 US\nTel:+(255)644-5939\nEmail:thompsonmatthew@example.com\nSite:http://www.jackson.com!\n\nGSTIN: OG@AAMFCO376K124\n\nEMS QUANTITY, PRICE\nTop language. +00 $87.69\nou. 2.00 $53.98\n\nPer he together co 3.00 $97.80\nExpert society. 6.00 $5331\n\nTotal in words: eight hundred and thirt-\ny-five point eight three\n\nBank Name — Central Bank of California\nBranch Name Raf CAMP.\n\nBank Account Number 18212245\n\nBank Swift Code SBININBB250\n\nNote:Total payment due in 14 days.\n\n‘SUB_TOTAL : 808.91 USD\nDISCOUNT(4.93%): (-) 39.88.\nTAX:VAT (6.06%): 49.00 USD\n\nTOTAL : 835.83 USD", "target_text": "{\"seller\": {\"name\": \"Markville, AK 58294 US.\", \"email\": \"melvindo@example.net\"}, \"buyer\": {}, \"invoice\": {\"date\": \"21-Jul-1995\", \"due_date\": \"07-May-1998\"}, \"items\": [], \"sub_total\": \"808.91\", \"due_amount\": \"835.83\", \"currency\": \"USD\", \"amount_in_words\": \"eight hundred and thirt-\", \"notes\": \"Total payment due in 14 days.\"}"}
{"input_text": "Address:16424 Timothy Mission\nMarkville, AK 58294 US.\n\nEmail:melvindo@example.net\n‘www.ThompsonandSons.org\n(GSTIN: 12345670 00070007\n\nTAX INVOICE\n\nDate: 05-Jul-2002\nDue Date : 20-Mar-2022\nPO Number :19\n\nBill o:Danielle Bernard\n476 Michael Knoll\n\nNicolefort, UT 64209 US\nTel:+(230)837-6011\nEmail:kevin82@example.org\nSite:https://www.blackwell.com/\n\nGSTIN: OG@AAMFCO376K124\n\nTEMS QUANTITY PRICE\n‘Before information energy 6.00 $69.83\nFish task believe general 4.00 $85.98\nEconomy explain magazine. 4.00 3723,\nIssue only rade, 4.00 s2071\n\nMind 5.00 $7153\n\nTotal in words: one thousand, three hundre-\n\nd and five point three one\nBank Name Central Bank of Texas\n\nBranch Name Raf CAMP.\nBank Account Number 19514786\nBank Swift Code SBININBB250\n\nNote:\nThis order is shipped through blue dart couri\n\n‘SUB_TOTAL : 1268.11 §\nDISCOUNT(1.24%): (-) 15.72\nTAX:VAT (5.83%): 73.98 $\n\nTOTAL : 1305.31 §", "target_text": "{\"seller\": {\"name\": \"Markville, AK 58294 US.\", \"email\": \"melvindo@example.net\"}, \"buyer\": {}, \"invoice\": {\"due_date\": \"20-Mar-2022\"}, \"items\": [{\"price\": \".\", \"quantity\": \"4.00\", \"amount\": \"3723,\"}], \"sub_total\": \"1268.11\", \"due_amount\": \"1305.31\", \"currency\": \"\", \"amount_in_words\": \"one thousand, three hundre-\", \"notes\": \"This order is shipped through blue dart couri\"}"}
{"input_text": "Address:16424 Timothy Mission\nMarkville, AK 58294 US\n\nEmail:melvindo@example.net\n‘www.ThompsonandSons.org\n(GSTIN: 12345670 00070007\n\nINVOICE\n\nInvoice Date: 04-Oct-2018\nDue Date : 16-Feb-2004\nPO Number :36\n\nBuyer :Adrienne Haynes\n\n310 Aguirre Club Suite 392\nNew Scott, LA 78952 US\nTel:+(888)197-2951\nEmail:pamjones@example.com\nSite:http://doyle-buckley.org/\n\nGSTIN: OG@AAMFCO376K124\n\nTEMS QUANTITY, PRICE\nStructure police hospital 1.00 S287\nLook thought 5.00 $35.08\n\nTotal in words: two hundred and f\nive point two nine\n\nBank Name State Bank of USA\nBranch Name Raf CAMP.\n\nBank Account Number 13031947\nBank Swift Code SBININBB250\n\nNote:Total payment due in 14 days.\n\n‘SUB_TOTAL : 197.07 EUR\nDISCOUNT(4.36%): (.) 8.59\nTAX:VAT (6.08%): 11.98 EUR\n\nTOTAL : 205.29 EUR", "target_text": "{\"seller\": {\"name\": \"Markville, AK 58294 US\", \"email\": \"melvindo@example.net\"}, \"buyer\": {\"name\": \"310 Aguirre Club Suite 392\"}, \"invoice\": {\"date\": \"04-Oct-2018\", \"due_date\": \"16-Feb-2004\"}, \"items\": [], \"sub_total\": \"197.07\", \"due_amount\": \"205.29\", \"currency\": \"EUR\", \"amount_in_words\": \"two hundred and f\", \"notes\": \"Total payment due in 14 days.\"}"}
{"input_text": "Address:16424 Timothy Mission\nMarkville, AK 58294 US.\n\nEmail:melvindo@example.net\n‘www.ThompsonandSons.org\n(GSTIN: 12345670 00070007\n\nINVOICE\n\nDate: 10-Sep-2013\nDue Date : 06-Apr-1994\n\nBuyer :Amber Ward\n673 Hunt Drives Apt. 647\n\nLake Christopher, CT 82747 US\nTol:+(183)928-6209\nEmail:zbond@example.org\nSite:http://www johnson.com/\n\nGSTIN: OG@AAMFCO376K124\n\nTEMS QUANTITY PRICE\nRealy, 100 $4489\n\nLow fight science, 6.00 $96.85\n“Trade general 2.00 $91.58\n‘Away goal hour. 6.00 $44.09\nIndividual bed month real 3.00 $39.20\n\nTotal in words: one thousand, two hundre-\nd and ten point two nine\n\nBankName Central Bank of Europe\nBranch Name Raf CAMP.\n\nBank Account Number 17814939\n\nBank Swift Code SBININBB250\n\n‘Thank you for choosing us!\n\nSUB_TOTAL : 1191.29 §\nDISCOUNT(1.05%): (-) 12.51\nTAX:VAT (3.26%): 38.78 $\n\nTOTAL : 1210.29 §", "target_text": "{\"seller\": {\"name\": \"Markville, AK 58294 US.\", \"email\": \"melvindo@example.net\"}, \"buyer\": {\"name\": \"673 Hunt Drives Apt. 647\"}, \"invoice\": {\"due_date\": \"06-Apr-1994\"}, \"items\": [], \"sub_total\": \"1191.29\", \"due_amount\": \"1210.29\", \"currency\": \"\", \"amount_in_words\": \"one thousand, two hundre-\", \"notes\": \"\"}"}
{"input_text": "Address:16424 Timothy Mission\nMarkville, AK 58294 US\n\nEmail:melvindo@example.net\n‘www.ThompsonandSons.org\n(GSTIN: 12345670 00070007\n\nINVOICE\n\nInvoice Date: 13-Jun-2019\nDue Date : 22-May-2022\nPO Number :63\n\nBill o:James Miller\n41839 Lee Terrace Apt. 982\nLake Gregoryland, WV 71038 US\nTol:+(553)734-0642\nEmail:zjohnson@example.com\nSite:https://smith.com/\n\nGSTIN: OG@AAMFCO376K124\n\nTEMS QUANTITY, PRICE\nSing send while 1.00 $3151\nSee population 4.00 s2082\n\nTotal in words: one hundred and fifty~\nthree point five three\n\nBankName State Bank of England\nBranch Name Raf CAMP.\n\nBank Account Number 15655075\n\nBank Swift Code SBININBB250\n\n‘Thank you for choosing us!\n\n‘SUB_TOTAL : 150.79 $\nDISCOUNT(4.68%): (-) 7.06\nTAX:VAT (5.84%): 8.80 $\n\nTOTAL : 153.53 §", "target_text": "{\"seller\": {\"name\": \"Markville, AK 58294 US\", \"email\": \"melvindo@example.net\"}, \"buyer\": {}, \"invoice\": {\"date\": \"13-Jun-2019\", \"due_date\": \"22-May-2022\"}, \"items\": [], \"sub_total\": \"150.79\", \"due_amount\": \"153.53\", \"currency\": \"\", \"amount_in_words\": \"one hundred and fifty\", \"notes\": \"\"}"}
{"input_text": "COMMERCIAL INVOICE\n\nPatel Reid INVOICE ID INV/54-95/365\nAddress:223 Kristen Mission Suite 986 Note: All payments to be made in cash.\nHernandezport, DE 40016 US Contact us for queries on these quotations.\n\nInvoice Date: 06-Mar-2001\n\nEmail:rivassarah@example.org\n\nBuyer :Tyler Cross,\n07444 Ward Ridges\n\nLisamouth, OK 62194 US\nTel:+(155)816-6371\nEmail:vanessa08@example.com\nSite:http://barnett-holmes.com/\n\n# ID Item name Quantity Unit price Amount\n1 135683. Front down audience. 6.00 $88.28 $529.68\n2 377421. Better four. 4.00 $84.33 $337.32\n3 317806 Section cover. 3.00 $45.22 $135.66\n\n‘SUB_TOTAL : 1002.66 EUR", "target_text": "{\"seller\": {\"name\": \"Patel Reid INVOICE ID INV/54-95/365\", \"email\": \"rivassarah@example.org\"}, \"buyer\": {\"name\": \"07444 Ward Ridges\"}, \"invoice\": {\"date\": \"06-Mar-2001\"}, \"items\": [{\"price\": \"529.68\", \"quantity\": \"2\", \"amount\": \"377421.\"}, {\"price\": \"337.32\", \"quantity\": \"3\", \"amount\": \"317806\"}], \"sub_total\": \"1002.66\", \"due_amount\": null, \"currency\": \"\", \"amount_in_words\": \"\", \"notes\": \"All payments to be made in cash.\\nHernandezport, DE 40016 US Contact us for queries on these quotations.\"}"}
{"input_text": "Address:16424 Timothy Mission\nMarkville, AK 58294 US.\n\nEmail:melvindo@example.net\n‘www.ThompsonandSons.org\n(GSTIN: 12345670 00070007\n\nTAX INVOICE\n\nDate: 17-Apr-2018\nDue Date : 17-Jun-2017\n\nBuyer John Lawson\n65976 Shane Flat Apt. 654\nJanetmouth, ID 41734 US\nTel:+(907)929-8719\nEmail:hammondholly@example.com\nSite:https://robertson.com/\n\nGSTIN: OG@AAMFCO376K124\n\nTEMS QUANTITY PRICE\nPas. 100 $49.96\nProvide fear 6.00 s79.47\nFula 2.00 sorar\n\nOur receive sep. 3.00 $7607\n‘Along hour 3.00 $7388\n\nTotal in words: one thousand and seven-\nty-one point eight nine\n\nBank Name State Bank of USA\nBranch Name Raf CAMP.\n\nBank Account Number 11539956\n\nBank Swift Code SBININBB250\n\nNote:Total payment due in 14 days.\n\n‘SUB_TOTAL : 1037.57 USD\nDISCOUNT(3.22%): (-) 33.44\nTAX:VAT (6.17%): 63.99 USD\n\nTOTAL : 1071.89 USD", "target_text": "{\"seller\": {\"name\": \"Markville, AK 58294 US.\", \"email\": \"melvindo@example.net\"}, \"buyer\": {}, \"invoice\": {\"due_date\": \"17-Jun-2017\"}, \"items\": [], \"sub_total\": \"1037.57\", \"due_amount\": \"1071.89\", \"currency\": \"USD\", \"amount_in_words\": \"one thousand and seven-\", \"notes\": \"Total payment due in 14 days.\"}"}
{"input_text": "Address:16424 Timothy Mission\nMarkville, AK 58294 US.\n\nEmail:melvindo@example.net\n‘www.ThompsonandSons.org\n(GSTIN: 12345670 00070007\n\nCOMMERCIAL INVOICE\n\nInvoice Date: 11-Mar-2016\nDue Date : 11-Mar-2009\nPO Number :74\n\nBill o:James Diaz\n35003 Mark Forest Apt. 586\n\nLake Ronaldton, CA 36947 US\nTel:+(409)452-2450\nEmail:theresacook@example.com\nSite:http://www.miller.com/\n\nGSTIN: OG@AAMFCO376K124\n\nEMS QUANTITY, PRICE\nNumber everybody, +00 $712\nExparionce family station assume, 6.00 S016\nFigure body 2.00 $59.47\n\nPoint bive out 1.00 $43.83\n\nTotal in words: seven hundred and twent-\n\nyeeight point zero five\nBank Name Central Bank of Texas\n\nBranch Name Raf CAMP.\nBank Account Number 15737646\nBank Swift Code SBININBB250\n\nNote: All payments to be made in cash.\nContact us for queries on these quotations.\n\n‘SUB_TOTAL : 721.05 USD\nDISCOUNT(4.35%): (.) 31.37.\nTAX:VAT (5.19%): 37.43 USD\n\nTOTAL : 728.05 USD", "target_text": "{\"seller\": {\"name\": \"Markville, AK 58294 US.\", \"email\": \"melvindo@example.net\"}, \"buyer\": {}, \"invoice\": {\"date\": \"11-Mar-2016\", \"due_date\": \"11-Mar-2009\"}, \"items\": [], \"sub_total\": \"721.05\", \"due_amount\": \"728.05\", \"currency\": \"USD\", \"amount_in_words\": \"seven hundred and twent-\", \"notes\": \"All payments to be made in cash.\\nContact us for queries on these quotations.\"}"}
{"input_text": "Address:16424 Timothy Mission\nMarkville, AK 58294 US.\n\nEmail:melvindo@example.net\n‘www.ThompsonandSons.org\n(GSTIN: 12345670 00070007\n\nINVOICE\n\nInvoice Date: 14-Nov-1999\nDue Date : 07-Dec-2018\nPO Number :92\n\nBill o:Susan Ryan\n‘5691 Myers Path Apt. 109\nLake Nicholas, MD 31568 US.\nTol:+(189)984-0819\nEmailioevans@example.com\nSite:https://mason.infol\n\nGSTIN: OG@AAMFCO376K124\n\nTEMS QUANTITY PRICE\n‘News fi 2.00 $4073\n‘tention ready radio +00 453\n‘Staff wo oficer amount. 3.00 366.71\nlass future. 4.00 $86.31\n\nSay project. 5.00 $55.41\n\nTotal in words: nine hundred and th\nty-one point zero nine\n\nBankName State Bank of Texas.\nBranch Name Raf CAMP.\n\nBank Account Number 12438592\nBank Swift Code SBININBB250\n\n‘Thank you for choosing us!\n\n‘SUB_TOTAL : 916.41 USD\nDISCOUNT(1.04%): (-) 9.53.\nTAX:VAT (6.03%): 55.28 USD\n\nTOTAL : 931.09 USD", "target_text": "{\"seller\": {\"name\": \"Markville, AK 58294 US.\", \"email\": \"melvindo@example.net\"}, \"buyer\": {}, \"invoice\": {\"date\": \"14-Nov-1999\", \"due_date\": \"07-Dec-2018\"}, \"items\": [{\"price\": \".\", \"quantity\": \"3.00\", \"amount\": \"366.71\"}], \"sub_total\": \"916.41\", \"due_amount\": \"931.09\", \"currency\": \"USD\", \"amount_in_words\": \"nine hundred and th\", \"notes\": \"\"}"}
{"input_text": "Address:16424 Timothy Mission\nMarkville, AK 58294 US.\n\nEmail:melvindo@example.net\n‘www.ThompsonandSons.org\n(GSTIN: 12345670 00070007\n\nTAX INVOICE\n\nDate: 03-Feb-1997\nDue Date : 22-Nov-2001\nPO Number :82\n\nBill o:Linda Shaw\n9258 Jonathan Ville Suite 521\n‘South Kathy, SC 35233 US\nTel:+(403)747-6395\nEmail:tatkins@example.org\nSite:https://www.price-paul.net/\n\nGSTIN: OG@AAMFCO376K124\n\nEMS (QUANTITY, PRICE\nReach federal also, 2.00 $9974\nNight serve its. 5.00 $77.09\nOff size fear 2.00 $3272\nStructure milion nancial 4.00 $63.23\n\nTotal in words: nine hundred and tw-\nenty-one point eight\n\nBankName State Bank of Texas.\nBranch Name Raf CAMP.\n\nBank Account Number 11975800\nBank Swift Code SBININBB250\n\n‘Thank you for your business!\n\n‘SUB_TOTAL : 903.29 $\nDISCOUNT(3.38%): (-) 30.53,\nTAX:VAT (5.14%): 46.42 $\n\nTOTAL : 921.80", "target_text": "{\"seller\": {\"name\": \"Markville, AK 58294 US.\", \"email\": \"melvindo@example.net\"}, \"buyer\": {}, \"invoice\": {\"due_date\": \"22-Nov-2001\"}, \"items\": [], \"sub_total\": \"903.29\", \"due_amount\": \"921.80\", \"currency\": \"\", \"amount_in_words\": \"nine hundred and tw-\", \"notes\": \"\"}"}
{"input_text": "Address:16424 Timothy Mission\nMarkville, AK 58294 US.\n\nEmail:melvindo@example.net\n‘www.ThompsonandSons.org\n(GSTIN: 12345670 00070007\n\nINVOICE\n\nDate: 31-May-1999\nDue Date : 31-Jul-2000\n\nBill o:Janet West\n490 Melinda Streets Apt. 806\nLauramouth, 1D 47708 US\nTel:+(122)911-9920\nEmail:wrobinson@example.com\nSite:http://www.stephenson-murphy.info!\n\nGSTIN: OG@AAMFCO376K124\n\nEMS QUANTITY, PRICE\nMovement development 4.00 $6231\n‘Compare tough 1.00 57564\n‘Scone suffer. 1.00 $95.08\nLeave new. 6.00 $52.64\n\nTotal in words: seven hundred and for-\nty:nine point one six\n\nBankName State Bank of Europe\nBranch Name Raf CAMP.\n\nBank Account Number 15818589\n\nBank Swift Code SBININBB250\n\n‘Thank you for choosing us!\n\n‘SUB_TOTAL : 735.75 USD\nDISCOUNT(1.39%): (.) 10.23\nTAX:VAT (5.80%): 42.69 USD\n\nTOTAL : 749.16 USD", "target_text": "{\"seller\": {\"name\": \"Markville, AK 58294 US.\", \"email\": \"melvindo@example.net\"}, \"buyer\": {}, \"invoice\": {\"due_date\": \"31-Jul-2000\"}, \"items\": [], \"sub_total\": \"735.75\", \"due_amount\": \"749.16\", \"currency\": \"USD\", \"amount_in_words\": \"seven hundred and for-\", \"notes\": \"\"}"}
{"input_text": "Address:16424 Timothy Mission\nMarkville, AK 58294 US.\n\nEmail:melvindo@example.net\n‘www.ThompsonandSons.org\n(GSTIN: 12345670 00070007\n\nINVOICE\n\nDate: 14-Oct-2011\nDue Date : 19-Apr-2018\n\nBuyer :Alexis Burgess\n217 Jacob Alley Apt. 066\nPort Heather, AL 17209 US\nTol:+(075)927-7182\nEmail:vwaters@example.org\nSite:https://www.barber.com/\n\nGSTIN: OG@AAMFCO376K124\n\nTEMS QUANTITY PRICE\nProcess year happen altack 3.00 $66.98\nProperty whatever. 500 $62.21\nMatter daughter 5.00 s3t2t\n\nTree score way. 2.00 $23.06\nTown represent 6.00 $98.26\n\nTotal in words: one thousand, three hundred a-\nId fifty-five point nine three\n\nBank Name Central Bank of Europe\nBranch Name Raf CAMP.\n\nBank Account Number 19543799\n\nBank Swift Code SBININBB250\n\nNote: All payments to be made in cash.\nContact us for queries on these quotations.\n\n‘SUB_TOTAL : 1303.60 §\nDISCOUNT(2.83%): (-) 36.89\nTAX:VAT (5.42%): 70.74 $\n\nTOTAL : 1355.93 §", "target_text": "{\"seller\": {\"name\": \"Markville, AK 58294 US.\", \"email\": \"melvindo@example.net\"}, \"buyer\": {\"name\": \"217 Jacob Alley Apt. 066\"}, \"invoice\": {\"due_date\": \"19-Apr-2018\"}, \"items\": [], \"sub_total\": \"1303.60\", \"due_amount\": \"1355.93\", \"currency\": \"\", \"amount_in_words\": \"one thousand, three hundred a-\", \"notes\": \"All payments to be made in cash.\\nContact us for queries on these quotations.\"}"}
{"input_text": "Jensen Grouy COMMERCIAL INVOICE\n‘Address:496 Buck Rest Suite 598\nJenningsburgh, UT 95460 US\n\nINVOICE ID 6522-278\n\nDate: 15-Oct-2007\nDue Date : 06-Jan-2005\n\n‘SHIP_TO:\nJudy Montoya\n\n26373 Bailey Circles\n\nNorth Stovenchester, MO 12312 US\n\nEmail:sandra60@exampl\nSite:https:/Ihenderson-parks.biz!\n\nDescription ‘QUANTITY PRICE\nLawyer during “400 $97.19\n‘Amost able administration, 4100 $38.20\n\n‘Terms and Conditions\nwill be charged if payment is not made within the due date.", "target_text": "{\"seller\": {\"name\": \"Jenningsburgh, UT 95460 US\", \"email\": \"sandra60@exampl\"}, \"buyer\": {}, \"invoice\": {\"due_date\": \"06-Jan-2005\"}, \"items\": [], \"sub_total\": null, \"due_amount\": null, \"currency\": \"\", \"amount_in_words\": \"\", \"notes\": \"\"}"}
{"input_text": "COMMERCIAL INVOICE\n\nINVOICE # 6yoMSd-524\nInvoice Date: 24-Apr-2020\n\nSHIP_TO:\nDavid Berry\n\n£81629 Jones Fields\n\nDouglasfurt, MO $7053 US.\nTol:+(839)417-7542\nEmail:patricia30@example.org\nSite:https:/tumphrey-mendez.info!\n\n(6.00 Kid physical environment age.\n3,00 | Question everything.\nTotal in words: six hundred and twenty- SUB_TOTAL : 607.14 EUR\n\n-four point eight seven\n\n‘Terms and Conditions\nwill bo charged if payment is not made within the due date.", "target_text": "{\"seller\": {\"name\": \"INVOICE # 6yoMSd-524\", \"email\": \"patricia30@example.org\"}, \"buyer\": {}, \"invoice\": {\"number\": \"6yoMSd-524\", \"date\": \"24-Apr-2020\"}, \"items\": [], \"sub_total\": \"607.14\", \"due_amount\": null, \"currency\": \"\", \"amount_in_words\": \"six hundred and twenty- SUB_TOTAL\", \"notes\": \"\"}"}
{"input_text": "COMMERCIAL INVOICE\n\nInvoice number INV/65-19/034\nDate: 27-May-2013\n\nSHIP_TO:\n\nRowemouth, DC 01012 US\nTel:+(388)653-1543\nEmail:davidcoleman@example.net\nSite:https:/iwong-williams.com!\n\nQty Amount\n6.00 568.98.\n5.00. du 167.05.\n2.00 Protect hope. 35.18\n5.00 | Speech._ 429.90\n\nTotal in words: one thousand, two hundred -\nand fifteen point three two\n\n4. Please send payment within 8 days of receiving this invoice.\n‘There will be a 2.5% intrest charge per month on late invoices.\n2. Please include the Invoice number in your payment notes.\n\nSUB_TOTAL : 1201.11 USD", "target_text": "{\"seller\": {\"name\": \"Date: 27-May-2013\", \"email\": \"davidcoleman@example.net\"}, \"buyer\": {}, \"invoice\": {}, \"items\": [{\"price\": \"6.00\", \"quantity\": \"568.98.\", \"amount\": \"5.00.\"}, {\"price\": \".\", \"quantity\": \"35.18\", \"amount\": \"5.00\"}], \"sub_total\": \"1201.11\", \"due_amount\": null, \"currency\": \"\", \"amount_in_words\": \"one thousand, two hundred -\", \"notes\": \"s.\"}"}
{"input_text": "COMMERCIAL INVOICE\n\nInvoice number 1Y2M9d-341,\nInvoice Date: 21-Mar-2003\n\nAddress:785 Kaiser Circles Suite 840 866 Amanda Overpass\n\nWest Johnny, KS 33272 US\n\nRoyport, GU 62057 US\nTol:+(515)672-7619\nEmail:wedwards@example.not\nSite:http:/Isanchez.com!\n\nLoty lip Description Unit price | Amount\n3.00 | 508713 _| Glass later. 67.50 202.50\n15.00 _|484348 _| Best personal sinos 62.93 314.6\n6.00 __|558072 _| Price. 25.23 151.38\n3.00 | 560785 _| Cold some action 81.69 45.07\n2.00 | 948160 | writer between mention. 34.78 69.56.\n\n‘SUB_TOTAL : 983.16 USD\n\nTAX:VAT (5.03%): 49.45 USD\n\nTOTAL : 1009.01 USD", "target_text": "{\"seller\": {\"name\": \"West Johnny, KS 33272 US\", \"email\": \"wedwards@example.not\"}, \"buyer\": {}, \"invoice\": {\"date\": \"21-Mar-2003\"}, \"items\": [{\"price\": \".\", \"quantity\": \"67.50\", \"amount\": \"202.50\"}, {\"price\": \"62.93\", \"quantity\": \"314.6\", \"amount\": \"6.00\"}, {\"price\": \".\", \"quantity\": \"25.23\", \"amount\": \"151.38\"}, {\"price\": \"81.69\", \"quantity\": \"45.07\", \"amount\": \"2.00\"}, {\"price\": \".\", \"quantity\": \"34.78\", \"amount\": \"69.56.\"}], \"sub_total\": \"983.16\", \"due_amount\": \"1009.01\", \"currency\": \"USD\", \"amount_in_words\": \"\", \"notes\": \"\"}"}
{"input_text": "Duran, Morgan and Lopez\n\nAddress:4901 Long Walll Apt. 620\nJoshuaville, CT 95783 US.\n\nGSTIN 336SPTNO37LG120\n\nBill to:Jared Jordan\n31794 Jones Ray\nWolfeside, WA 46862 US\nTel:+(788)491-4206\nEmail:ryan69@example.com\nSite:http://wiliams.com/\n\nGSTIN 22AAAAADOO0A125,\n\nDate: 23-May-2020\n\nTAX INVOICE\n\nINVOICE ID INV/73-16/177\n\nDue Date : 11-Mar-1994\n\nTEMS (QUANTITY, PRICE,\nIdentity right source. 5.00 $35.50\nSocial 4.00 $8265\n\n“Serious indeed avaiable, 3.00 $76.36\n\n‘SUB_TOTAL : 737.18 EUR\n\nGST(18%) : 132.69\n\nBALANCE DUE :\n\n48.86 EUR", "target_text": "{\"seller\": {\"name\": \"Duran, Morgan and Lopez\", \"email\": \"ryan69@example.com\"}, \"buyer\": {\"name\": \"31794 Jones Ray\"}, \"invoice\": {\"due_date\": \"11-Mar-1994\"}, \"items\": [], \"sub_total\": \"737.18\", \"due_amount\": null, \"currency\": \"\", \"amount_in_words\": \"\", \"notes\": \"\"}"}
{"input_text": "Buyer :Hannah Soto\n\n‘Address:047 Jackson Meadows Apt. 391 Ges Domine. Greve Suite 570\nPearsonmouth, OH 83042 US Launestad, GU 24610 US\nTel:+(259)741-2905\nEmail:powellpatricia@example.net\nGSTIN No, 24AADCP1453/AZZ, Site:http://meyers.com/\n\nTAX INVOICE Invoice number 8657-037\nInvoice Date: 21-Nov-1994\n\nItem Price Quantity Amount\nParticipant other. 28.11 1.00 28.11\nCard job decision opportunity, 58.67 5.00 293.35\nChallenge surface factor. 74.88 4.00 299.52\nTrial pay. 89.88 3.00 269.64\nThey grow moment. 68.02 5.00 340.10\n\nDUE_AMOUNT : 1239.71 USD\n\nTotal in words: one thousand, two hundred an-\nd thirty-nine point seven one\n\n‘SUB_TOTAL : 1230.72 USD\n\nNote: All payments to be made in cash.\nContact us for queries on these quotations.", "target_text": "{\"seller\": {\"name\": \"Pearsonmouth, OH 83042 US Launestad, GU 24610 US\", \"email\": \"powellpatricia@example.net\"}, \"buyer\": {\"name\": \"‘Address:047 Jackson Meadows Apt. 391 Ges Domine. Greve Suite 570\"}, \"invoice\": {\"date\": \"21-Nov-1994\"}, \"items\": [{\"price\": \".\", \"quantity\": \"28.11\", \"amount\": \"1.00\"}, {\"price\": \",\", \"quantity\": \"58.67\", \"amount\": \"5.00\"}, {\"price\": \".\", \"quantity\": \"74.88\", \"amount\": \"4.00\"}, {\"price\": \".\", \"quantity\": \"89.88\", \"amount\": \"3.00\"}, {\"price\": \".\", \"quantity\": \"68.02\", \"amount\": \"5.00\"}], \"sub_total\": \"1230.72\", \"due_amount\": null, \"currency\": \"\", \"amount_in_words\": \"one thousand, two hundred an-\", \"notes\": \"All payments to be made in cash.\\nContact us for queries on these quotations.\"}"}
{"input_text": "Address:16424 Timothy Mission\nMarkville, AK 58294 US.\n\nEmail:melvindo@example.net\n‘www.ThompsonandSons.org\n(GSTIN: 12345670 00070007\n\nCOMMERCIAL INVOICE\n\nInvoice Date: 28-Apr-2009\nDue Date : 16-Oct-2005\n\nBill to:Monica Fuller\n866 Thomas Ways Suite 262\nNew Tonya, KS 08465 US\nTol:+(783)572-8210\nEmail:bryce74@example.org\nSite:http://gill.com!\n\nGSTIN: OG@AAMFCO376K124\n\nEMS QUANTITY, PRICE\n‘Atle usually must 3.00 $52.18\nHome collection elec federal 3.00 $55.65\n{Gareer foreign chi 1.00 $25.11\nVote one, 5.00 $1933\n\nTotal in words: four hundred and for-\nty-one point one one\n\nBankName State Bank of England\nBranch Name Raf CAMP.\n\nBank Account Number 13043063\n\nBank Swift Code SBININBB250\n\nNote:\nThis order is shipped through blue dart couri\n\nSUB_TOTAL : 445.25 $\nDISCOUNT(2.87%): (.) 12.78\nTAX:VAT (3.73%): 16.61 $\n\nTOTAL: 441.115", "target_text": "{\"seller\": {\"name\": \"Markville, AK 58294 US.\", \"email\": \"melvindo@example.net\"}, \"buyer\": {\"name\": \"866 Thomas Ways Suite 262\"}, \"invoice\": {\"date\": \"28-Apr-2009\", \"due_date\": \"16-Oct-2005\"}, \"items\": [], \"sub_total\": \"445.25\", \"due_amount\": \"441.115\", \"currency\": \"\", \"amount_in_words\": \"four hundred and for-\", \"notes\": \"This order is shipped through blue dart couri\"}"}
